redapy/__init__.py
redapy/artist.py
redapy/base.py
redapy/forum/subscriptions.py
redapy/index.py
redapy/torrent/download.py
redapy/torrent/search.py
redapy/torrent/upload.py
redapy/user/bookmarks.py
redapy/user/user.py
redapy/utils/prepare_temp.py
redapy-0.1.dist-info/WHEEL
redapy-0.1.dist-info/METADATA
redapy-0.1.dist-info/RECORD
