Metadata-Version: 2.1
Name: redapy
Version: 0.1
Summary: API wrapper module for redacted.ch
License: MIT
Author: nagqu
Requires-Python: >=3.9,<4.0
Classifier: License :: OSI Approved :: MIT License
Classifier: Programming Language :: Python :: 3
Classifier: Programming Language :: Python :: 3.10
Classifier: Programming Language :: Python :: 3.9
Requires-Dist: python-dotenv (>=0.20.0,<0.21.0)
Requires-Dist: requests (>=2.28.1,<3.0.0)
